finbright_utils/__init__.py
finbright_utils/fin_statistics.py
finbright_utils/resample.py
finbright_utils/constants/definitions.py
finbright_utils/constants/errors.py
finbright_utils/constants/interval.py
finbright_utils-0.0.7.dist-info/METADATA
finbright_utils-0.0.7.dist-info/WHEEL
finbright_utils-0.0.7.dist-info/licenses/LICENSE
finbright_utils-0.0.7.dist-info/RECORD
